setup.cfg
setup.py
coinschedule/__init__.py
coinschedulepy.egg-info/PKG-INFO
coinschedulepy.egg-info/SOURCES.txt
coinschedulepy.egg-info/dependency_links.txt
coinschedulepy.egg-info/requires.txt
coinschedulepy.egg-info/top_level.txt