Metadata-Version: 1.1
Name: coinschedulepy
Version: 1.0.1
Summary: A python3 wrapper for the coinschedule api
Home-page: https://github.com/0x15f/coinschedule-python
Author: Jake Casto
Author-email: jakehcasto@aol.com
License: MIT
Keywords: ico icos coinschedule api python3
Platform: UNKNOWN
Classifier: Development Status :: 5 - Production/Stable
Classifier: Intended Audience :: Developers
Classifier: License :: OSI Approved :: MIT License
Classifier: Programming Language :: Python :: 3
Classifier: Programming Language :: Python :: 3.3
Classifier: Programming Language :: Python :: 3.4
Classifier: Programming Language :: Python :: 3.5
